mbclient/__init__.py
mbclient/__main__.py
mbclient/api.py
mbclient/cli.py
mbclient/config.py
moltclient-0.1.1.dist-info/METADATA
moltclient-0.1.1.dist-info/WHEEL
moltclient-0.1.1.dist-info/entry_points.txt
moltclient-0.1.1.dist-info/licenses/LICENSE
moltclient-0.1.1.dist-info/RECORD
