Metadata-Version: 2.4
Name: moltClient
Version: 0.1.1
Summary: Moltbook CLI client
Project-URL: Repository, https://github.com/Starry-Sky-World/MBClient
Author: Moltbook CLI Contributors
License: GPL-3.0-or-later
License-File: LICENSE
Keywords: bot,cli,httpx,moltbook
Classifier: Environment :: Console
Classifier: License :: OSI Approved :: GNU General Public License v3 or later (GPLv3+)
Classifier: Programming Language :: Python :: 3
Classifier: Programming Language :: Python :: 3.12
Classifier: Topic :: Internet
Requires-Python: >=3.12
Requires-Dist: httpx>=0.28.1
